tele_api_python/__init__.py
tele_api_python/api/__init__.py
tele_api_python/api/default_api.py
tele_api_python/api_client.py
tele_api_python/api_response.py
tele_api_python/configuration.py
tele_api_python/exceptions.py
tele_api_python/models/__init__.py
tele_api_python/models/affiliate_info.py
tele_api_python/models/animation.py
tele_api_python/models/answer_callback_query_post_request.py
tele_api_python/models/answer_inline_query_post_request.py
tele_api_python/models/answer_pre_checkout_query_post_request.py
tele_api_python/models/answer_shipping_query_post_request.py
tele_api_python/models/answer_web_app_query_post200_response.py
tele_api_python/models/answer_web_app_query_post_request.py
tele_api_python/models/approve_chat_join_request_post_request.py
tele_api_python/models/audio.py
tele_api_python/models/background_fill.py
tele_api_python/models/background_fill_freeform_gradient.py
tele_api_python/models/background_fill_gradient.py
tele_api_python/models/background_fill_solid.py
tele_api_python/models/background_type.py
tele_api_python/models/background_type_chat_theme.py
tele_api_python/models/background_type_fill.py
tele_api_python/models/background_type_pattern.py
tele_api_python/models/background_type_wallpaper.py
tele_api_python/models/ban_chat_member_post_request.py
tele_api_python/models/ban_chat_member_post_request_chat_id.py
tele_api_python/models/ban_chat_sender_chat_post_request.py
tele_api_python/models/birthdate.py
tele_api_python/models/bot_command.py
tele_api_python/models/bot_command_scope.py
tele_api_python/models/bot_command_scope_all_chat_administrators.py
tele_api_python/models/bot_command_scope_all_group_chats.py
tele_api_python/models/bot_command_scope_all_private_chats.py
tele_api_python/models/bot_command_scope_chat.py
tele_api_python/models/bot_command_scope_chat_administrators.py
tele_api_python/models/bot_command_scope_chat_member.py
tele_api_python/models/bot_command_scope_default.py
tele_api_python/models/bot_description.py
tele_api_python-1.0.0.dist-info/METADATA
tele_api_python-1.0.0.dist-info/WHEEL
tele_api_python-1.0.0.dist-info/RECORD
